torch3dr/__init__.py
torch3dr/Mesh/__init__.py
torch3dr/Mesh/mesh_utils.py
torch3dr/Rendering/__init__.py
torch3dr/Rendering/render_360.py
torch3dr/Rendering/render_dolly_effect.py
torch3dr/Rendering/rendering_utils.py
torch3dr/Rendering/Tests/__init__.py
torch3dr/Rendering/Tests/test_mesh_render.py
torch3dr-0.0.1.dist-info/LICENSE
torch3dr-0.0.1.dist-info/METADATA
torch3dr-0.0.1.dist-info/WHEEL
torch3dr-0.0.1.dist-info/top_level.txt
torch3dr-0.0.1.dist-info/RECORD
