Metadata-Version: 2.2
Name: torch3dr
Version: 0.0.1
Summary: A PyTorch-based library for 3D Vision Research
Home-page: https://github.com/amirhossein-razlighi/Torch3DR
Author: AmirHossein Razlighi
Author-email: arazlighi@gmail.com
Project-URL: Bug Tracker, https://github.com/amirhossein-razlighi/Torch3DR/issues
Classifier: Programming Language :: Python :: 3
Classifier: License :: CC0 1.0 Universal (CC0 1.0) Public Domain Dedication
Classifier: Operating System :: OS Independent
Requires-Python: >=3.10
License-File: LICENSE
Requires-Dist: torch>=1.9.0
Requires-Dist: numpy>=1.19.2
Requires-Dist: tqdm>=4.64.0
Requires-Dist: pillow~=11.1.0
Requires-Dist: imageio~=2.37.0
Requires-Dist: click~=8.1.8
Requires-Dist: pytorch3d
Dynamic: author
Dynamic: author-email
Dynamic: classifier
Dynamic: description
Dynamic: description-content-type
Dynamic: home-page
Dynamic: project-url
Dynamic: requires-dist
Dynamic: requires-python
Dynamic: summary
